tfga/__init__.py
tfga/blades.py
tfga/cayley.py
tfga/layers.py
tfga/mv.py
tfga/mv_ops.py
tfga/tfga.py
tfga-0.2.0.dist-info/WHEEL
tfga-0.2.0.dist-info/METADATA
tfga-0.2.0.dist-info/RECORD
