Metadata-Version: 2.1
Name: tfga
Version: 0.2.0
Summary: Clifford and Geometric Algebra with TensorFlow
Home-page: https://github.com/RobinKa/tfga
License: MIT
Keywords: geometric-algebra,clifford-algebra,tensorflow,multi-vector,para-vector,mathematics,machine-learning
Author: Robin Kahlow
Author-email: tora@warlock.ai
Requires-Python: >=3.8,<3.12
Classifier: Development Status :: 3 - Alpha
Classifier: Intended Audience :: Developers
Classifier: Intended Audience :: Education
Classifier: Intended Audience :: Science/Research
Classifier: License :: OSI Approved :: MIT License
Classifier: Programming Language :: Python :: 3
Classifier: Programming Language :: Python :: 3.8
Classifier: Programming Language :: Python :: 3.9
Classifier: Programming Language :: Python :: 3.10
Classifier: Programming Language :: Python :: 3.11
Classifier: Programming Language :: Python :: 3
Classifier: Programming Language :: Python :: 3 :: Only
Classifier: Programming Language :: Python :: 3.10
Classifier: Programming Language :: Python :: 3.11
Classifier: Programming Language :: Python :: 3.8
Classifier: Programming Language :: Python :: 3.9
Classifier: Topic :: Scientific/Engineering
Classifier: Topic :: Scientific/Engineering :: Artificial Intelligence
Classifier: Topic :: Scientific/Engineering :: Mathematics
Classifier: Topic :: Scientific/Engineering :: Physics
Classifier: Topic :: Software Development
Classifier: Topic :: Software Development :: Libraries
Classifier: Topic :: Software Development :: Libraries :: Python Modules
Provides-Extra: tf
Requires-Dist: numpy (>=1.20.0,<2.0.0)
Requires-Dist: tensorflow (>=2.11.0,<3.0.0) ; extra == "tf"
Project-URL: Documentation, https://tfga.warlock.ai/
Project-URL: Repository, https://github.com/RobinKa/tfga
